Workbook

Sheet Synthèse
A1: SYNTHÈSE DU BILAN (M€) - 31/12/2025
A3: Classe d'actif | B3: Valeur de marché | C3: Valeur comptable | D3: Plus/moins-value latente | E3: Poids (VM)
A4: Obligations souveraines | B4: =SUMIFS(Actifs!$I:$I,Actifs!$B:$B,A4) | C4: =SUMIFS(Actifs!$H:$H,Actifs!$B:$B,A4) | D4: =B4-C4 | E4: =B4/$B$9
A5: Obligations corporate | B5: =SUMIFS(Actifs!$I:$I,Actifs!$B:$B,A5) | C5: =SUMIFS(Actifs!$H:$H,Actifs!$B:$B,A5) | D5: =B5-C5 | E5: =B5/$B$9
A6: Actions | B6: =SUMIFS(Actifs!$I:$I,Actifs!$B:$B,A6) | C6: =SUMIFS(Actifs!$H:$H,Actifs!$B:$B,A6) | D6: =B6-C6 | E6: =B6/$B$9
A7: Immobilier | B7: =SUMIFS(Actifs!$I:$I,Actifs!$B:$B,A7) | C7: =SUMIFS(Actifs!$H:$H,Actifs!$B:$B,A7) | D7: =B7-C7 | E7: =B7/$B$9
A8: Monétaire | B8: =SUMIFS(Actifs!$I:$I,Actifs!$B:$B,A8) | C8: =SUMIFS(Actifs!$H:$H,Actifs!$B:$B,A8) | D8: =B8-C8 | E8: =B8/$B$9
A9: Total actif | B9: =SUM(B4:B8) | C9: =SUM(C4:C8) | D9: =B9-C9 | E9: =SUM(E4:E8)
A11: Passif
A12: Provisions mathématiques | B12: =SUM(Passif_ModelPoints!H:H)
A13: PPB | B13: =INDEX(Hypothèses!B:B,MATCH("ppb_initiale",Hypothèses!A:A,0))
A14: Fonds propres comptables (plug) | B14: =C9-B12-B13
A15: Fonds propres 'valeur de marché des actifs' (VM actifs - PM - PPB) | B15: =B9-B12-B13
A17: Segment | B17: PM (M€) | C17: TMG | D17: Poids
A18: Génération 2020-2025 | B18: =SUMIFS(Passif_ModelPoints!$H:$H,Passif_ModelPoints!$B:$B,A18) | C18: =INDEX(Passif_ModelPoints!$D:$D,MATCH(A18,Passif_ModelPoints!$B:$B,0)) | D18: =B18/$B$12
A19: Génération 2013-2019 | B19: =SUMIFS(Passif_ModelPoints!$H:$H,Passif_ModelPoints!$B:$B,A19) | C19: =INDEX(Passif_ModelPoints!$D:$D,MATCH(A19,Passif_ModelPoints!$B:$B,0)) | D19: =B19/$B$12
A20: Génération 2005-2012 | B20: =SUMIFS(Passif_ModelPoints!$H:$H,Passif_ModelPoints!$B:$B,A20) | C20: =INDEX(Passif_ModelPoints!$D:$D,MATCH(A20,Passif_ModelPoints!$B:$B,0)) | D20: =B20/$B$12
A21: Génération avant 2005 | B21: =SUMIFS(Passif_ModelPoints!$H:$H,Passif_ModelPoints!$B:$B,A21) | C21: =INDEX(Passif_ModelPoints!$D:$D,MATCH(A21,Passif_ModelPoints!$B:$B,0)) | D21: =B21/$B$12

Sheet Hypothèses
A1: Paramètre | B1: Valeur | C1: Description
A2: date_valorisation | B2: 31/12/2025 | C2: Date de valorisation
A3: horizon | B3: 50 | C3: Horizon de projection (années), run-off sans affaires nouvelles
A4: nb_scenarios | B4: 2000 | C4: Nombre de scénarios Monte-Carlo (variables antithétiques)
A5: graine | B5: 12345 | C5: Graine du générateur aléatoire
A6: hw_a | B6: 0.08 | C6: Hull-White : vitesse de retour à la moyenne
A7: hw_sigma | B7: 0.011 | C7: Hull-White : volatilité du taux court (absolue)
A8: corr_taux_actions | B8: 0.2 | C8: Corrélation taux / actions
A9: corr_actions_immo | B9: 0.5 | C9: Corrélation actions / immobilier
A10: vol_actions | B10: 0.18 | C10: Volatilité annuelle des actions
A11: vol_immo | B11: 0.09 | C11: Volatilité annuelle de l'immobilier
A12: div_actions | B12: 0.03 | C12: Taux de dividende actions
A13: loyer_immo | B13: 0.04 | C13: Taux de loyer immobilier
A14: taux_realisation_pvl | B14: 0.08 | C14: Part des plus-values latentes actions/immo réalisée chaque année
... A27: spread_reinvestissement | B27: 0.0035 | C27: Spread moyen des obligations de réinvestissement

Sheet Courbe_taux
A1: Maturité (ans) | B1: Taux zéro-coupon | C1: Prix ZC | D1: Taux forward 1 an | F1: Source : courbe illustrative construite pour le projet. En situation réelle, utiliser la courbe EIOPA (RFR) publiée.
A2: 1 | B2: 0.02 | C2: =1/(1+B2)^A2 | D2: =1/C2-1
A3: 2 | B3: 0.0205 | C3: =1/(1+B3)^A3 | D3: =C2/C3-1
A4: 3 | B4: 0.022 | C4: =1/(1+B4)^A4 | D4: =C3/C4-1
A5: 4 | B5: 0.02325 | C5: =1/(1+B5)^A5 | D5: =C4/C5-1
A6: 5 | B6: 0.0245 | C6: =1/(1+B6)^A6 | D6: =C5/C6-1
A7: 6 | B7: 0.0255 | C7: =1/(1+B7)^A7 | D7: =C6/C7-1
A8: 7 | B8: 0.0265 | C8: =1/(1+B8)^A8 | D8: =C7/C8-1
A9: 8 | B9: 0.02717 | C9: =1/(1+B9)^A9 | D9: =C8/C9-1
A10: 9 | B10: 0.02783 | C10: =1/(1+B10)^A10 | D10: =C9/C10-1
A11: 10 | B11: 0.0285 | C11: =1/(1+B11)^A11 | D11: =C10/C11-1
A12: 11 | B12: 0.029 | C12: =1/(1+B12)^A12 | D12: =C11/C12-1
A13: 12 | B13: 0.0295 | C13: =1/(1+B13)^A13 | D13: =C12/C13-1
A14: 13 | B14: 0.03 | C14: =1/(1+B14)^A14 | D14: =C13/C14-1
... A31: 30 | B31: 0.031 | C31: =1/(1+B31)^A31 | D31: =C30/C31-1

Sheet Actifs
A1: ID | B1: Classe d'actif | C1: Sous-classe | D1: Notation | E1: Coupon | F1: Maturité résiduelle (ans) | G1: Nominal (M€) | H1: Valeur comptable (M€) | I1: Valeur de marché (M€) | J1: Duration modifiée | K1: Spread de crédit | L1: Plus/moins-value latente (M€)
A2: FR100000 | B2: Obligations souveraines | C2: OAT/Bund | D2: AA | E2: 0.02125 | F2: 2 | G2: 25.64 | H2: 25.94 | I2: 25.68 | J2: 1.98 | K2: 0 | L2: =I2-H2
A3: FR100001 | B3: Obligations souveraines | C3: OAT/Bund | D3: AA | E3: 0.015 | F3: 4 | G3: 17.52 | H3: 17.83 | I3: 16.98 | J3: 3.91 | K3: 0 | L3: =I3-H3
A4: FR100002 | B4: Obligations souveraines | C4: OAT/Bund | D4: AA | E4: 0.0225 | F4: 4 | G4: 15.07 | H4: 14.94 | I4: 15.03 | J4: 3.87 | K4: 0 | L4: =I4-H4
A5: FR100003 | B5: Obligations souveraines | C5: OAT/Bund | D5: AA | E5: 0.03375 | F5: 4 | G5: 25.98 | H5: 25.79 | I5: 27.02 | J5: 3.81 | K5: 0 | L5: =I5-H5
A6: FR100004 | B6: Obligations souveraines | C6: OAT/Bund | D6: AA | E6: 0.03 | F6: 4 | G6: 22.33 | H6: 21.56 | I6: 22.91 | J6: 3.83 | K6: 0 | L6: =I6-H6
A7: FR100005 | B7: Obligations souveraines | C7: OAT/Bund | D7: AA | E7: 0.0225 | F7: 5 | G7: 11.65 | H7: 12 | I7: 11.55 | J7: 4.78 | K7: 0 | L7: =I7-H7
A8: FR100006 | B8: Obligations souveraines | C8: OAT/Bund | D8: AA | E8: 0.0225 | F8: 5 | G8: 10.19 | H8: 9.93 | I8: 10.1 | J8: 4.78 | K8: 0 | L8: =I8-H8
A9: FR100007 | B9: Obligations souveraines | C9: OAT/Bund | D9: AA | E9: 0.02875 | F9: 5 | G9: 25.06 | H9: 25.28 | I9: 25.57 | J9: 4.73 | K9: 0 | L9: =I9-H9
A10: FR100008 | B10: Obligations souveraines | C10: OAT/Bund | D10: AA | E10: 0.025 | F10: 5 | G10: 20.18 | H10: 19.97 | I10: 20.24 | J10: 4.76 | K10: 0 | L10: =I10-H10
A11: FR100009 | B11: Obligations souveraines | C11: OAT/Bund | D11: AA | E11: 0.03375 | F11: 7 | G11: 18.57 | H11: 18.86 | I11: 19.45 | J11: 6.36 | K11: 0 | L11: =I11-H11
A12: FR100010 | B12: Obligations souveraines | C12: OAT/Bund | D12: AA | E12: 0.015 | F12: 7 | G12: 10.91 | H12: 10.62 | I12: 10.13 | J12: 6.68 | K12: 0 | L12: =I12-H12
A13: FR100011 | B13: Obligations souveraines | C13: OAT/Bund | D13: AA | E13: 0.0275 | F13: 8 | G13: 24.63 | H13: 24.77 | I13: 24.74 | J13: 7.28 | K13: 0 | L13: =I13-H13
... A41: FR100039 | B41: Obligations corporate | C41: Corporate IG | D41: AA | E41: 0.03375 | F41: 19 | G41: 6.19 | H41: 6.07 | I41: 6.43 | J41: 14.32 | K41: 0 | L41: =I41-H41
A42: EQ01 | B42: Actions | C42: Actions zone euro | H42: 38 | I42: 46 | L42: =I42-H42
A43: EQ02 | B43: Actions | C43: Actions Europe hors zone euro | H43: 24 | I43: 28 | L43: =I43-H43
A44: EQ03 | B44: Actions | C44: Actions internationales | H44: 20 | I44: 26 | L44: =I44-H44
A45: RE01 | B45: Immobilier | C45: Bureaux | H45: 28 | I45: 31 | L45: =I45-H45
A46: RE02 | B46: Immobilier | C46: Commerces | H46: 12 | I46: 11 | L46: =I46-H46
A47: RE03 | B47: Immobilier | C47: Résidentiel (SCPI/SCI) | H47: 21 | I47: 28 | L47: =I47-H47
A48: MM01 | B48: Monétaire | C48: Trésorerie et OPCVM monétaires | H48: 50 | I48: 50 | J48: 0.1 | L48: =I48-H48

Sheet Passif_ModelPoints
A1: ID | B1: Segment | C1: Année de génération | D1: TMG | E1: Âge moyen | F1: Ancienneté (ans) | G1: Nb contrats | H1: Provision mathématique (M€) | I1: Taux de rachat observé 2025
A2: MP0000 | B2: Génération 2020-2025 | C2: 2021 | D2: 0 | E2: 63 | F2: 4 | G2: 36 | H2: 2.544 | I2: 0.0386
A3: MP0001 | B3: Génération 2020-2025 | C3: 2020 | D3: 0 | E3: 58 | F3: 5 | G3: 28 | H3: 2.488 | I3: 0.0405
A4: MP0002 | B4: Génération 2020-2025 | C4: 2025 | D4: 0 | E4: 59 | F4: 0 | G4: 57 | H4: 3.707 | I4: 0.0451
A5: MP0003 | B5: Génération 2020-2025 | C5: 2025 | D5: 0 | E5: 69 | F5: 0 | G5: 30 | H5: 1.974 | I5: 0.0501
A6: MP0004 | B6: Génération 2020-2025 | C6: 2022 | D6: 0 | E6: 80 | F6: 3 | G6: 118 | H6: 4.489 | I6: 0.033
A7: MP0005 | B7: Génération 2020-2025 | C7: 2020 | D7: 0 | E7: 74 | F7: 5 | G7: 207 | H7: 6.921 | I7: 0.0456
A8: MP0006 | B8: Génération 2020-2025 | C8: 2020 | D8: 0 | E8: 45 | F8: 5 | G8: 155 | H8: 3.486 | I8: 0.0354
A9: MP0007 | B9: Génération 2020-2025 | C9: 2022 | D9: 0 | E9: 52 | F9: 3 | G9: 77 | H9: 4.079 | I9: 0.0481
A10: MP0008 | B10: Génération 2020-2025 | C10: 2024 | D10: 0 | E10: 45 | F10: 1 | G10: 242 | H10: 3.212 | I10: 0.0453
A11: MP0009 | B11: Génération 2020-2025 | C11: 2024 | D11: 0 | E11: 54 | F11: 1 | G11: 58 | H11: 3.079 | I11: 0.0492
A12: MP0010 | B12: Génération 2020-2025 | C12: 2023 | D12: 0 | E12: 52 | F12: 2 | G12: 38 | H12: 1.728 | I12: 0.0496
A13: MP0011 | B13: Génération 2020-2025 | C13: 2025 | D13: 0 | E13: 60 | F13: 0 | G13: 72 | H13: 3.965 | I13: 0.0408
... A401: MP0399 | B401: Génération avant 2005 | C401: 1993 | D401: 0.025 | E401: 59 | F401: 32 | G401: 1 | H401: 0.106 | I401: 0.0421

Sheet Historique
A1: Année | B1: OAT 10 ans | C1: Taux servi moyen | D1: Taux de rachat observé | E1: Rendement actions (indice) | G1: Données synthétiques inspirées de l'historique de marché (indicatif, à remplacer par des données réelles si disponibles).
A2: 2005 | B2: 0.034 | C2: 0.042 | D2: 0.0243 | E2: -0.162
A3: 2006 | B3: 0.038 | C3: 0.0388 | D3: 0.0336 | E3: 0.064
A4: 2007 | B4: 0.043 | C4: 0.0373 | D4: 0.0381 | E4: 0.08
A5: 2008 | B5: 0.042 | C5: 0.0375 | D5: 0.0328 | E5: -0.318
A6: 2009 | B6: 0.036 | C6: 0.0374 | D6: 0.0294 | E6: -0.095
A7: 2010 | B7: 0.031 | C7: 0.0358 | D7: 0.0238 | E7: 0.143
A8: 2011 | B8: 0.033 | C8: 0.0333 | D8: 0.0281 | E8: 0.14
A9: 2012 | B9: 0.02 | C9: 0.032 | D9: 0.0236 | E9: -0.138
A10: 2013 | B10: 0.022 | C10: 0.0277 | D10: 0.0267 | E10: 0.099
A11: 2014 | B11: 0.008 | C11: 0.0251 | D11: 0.02 | E11: 0.254
A12: 2015 | B12: 0.009 | C12: 0.0218 | D12: 0.02 | E12: 0.21
A13: 2016 | B13: 0.004 | C13: 0.0193 | D13: 0.02 | E13: 0.053
... A22: 2025 | B22: 0.029 | C22: 0.023 | D22: 0.0402 | E22: 0.211
